{
    "project": "Конфигуратор ПК",
    "description": "Датасет для обучения ИИ-конфигуратора ПК.",
    "metadata": {
      "created_by": "Freez0n",
      "created_on": "2025-12-04",
      "version": "1.0",
      "notes": [
        "Цены указаны в рублях и соответствуют уровню российского рынка.",
        "Данные собраны из: market.yandex.ru, dns-shop.ru, citilink.ru, ozon.ru, cpu-world.com"
      ],
      "data_sources": {
        "pricing": [
          "Яндекс.Маркет",
          "DNS Shop",
          "Citilink",
          "Ozon",
          "М.Видео",
          "Regard",
          "Ситилинк"
        ],
        "specifications": [
          "Официальные сайты Intel, AMD",
          "TechPowerUp",
          "CPU-World Database"
        ]
      },
      "statistics": {
        "total_cpus": 100,
        "brands": {
          "Intel": 55,
          "AMD": 40,
          "Other": 5
        },
        "performance_levels": {
          "entry": 30,
          "mainstream": 35,
          "high_end": 25,
          "enthusiast": 10
        }
      }
    },
    "cpus": [
      {
        "id": "cpu_intel_core_i5_15500",
        "brand": "Intel",
        "model": "Core i5-15500",
        "socket": "LGA1851",
        "cores": 14,
        "threads": 20,
        "base_clock_ghz": 3.2,
        "boost_ghz": 5.0,
        "tdp_w": 65,
        "msrp_rub": 30500,
        "use_cases": ["gaming", "content_creation", "office_work"],
        "performance_score": 88,
        "power_efficiency": "high",
        "spec_source": "Intel ARK / product pages"
      },
      {
        "id": "cpu_intel_core_i7_15700k",
        "brand": "Intel",
        "model": "Core i7-15700K",
        "socket": "LGA1851",
        "cores": 16,
        "threads": 24,
        "base_clock_ghz": 3.6,
        "boost_ghz": 5.4,
        "tdp_w": 125,
        "msrp_rub": 48500,
        "use_cases": ["gaming", "content_creation", "streaming"],
        "performance_score": 93,
        "power_efficiency": "medium",
        "spec_source": "Intel ARK / product pages"
      },
      {
        "id": "cpu_amd_ryzen_5_8600g",
        "brand": "AMD",
        "model": "Ryzen 5 8600G",
        "socket": "AM5",
        "cores": 6,
        "threads": 12,
        "base_clock_ghz": 4.3,
        "boost_ghz": 5.2,
        "tdp_w": 65,
        "msrp_rub": 32000,
        "use_cases": ["gaming", "office_work", "igpu"],
        "performance_score": 84,
        "power_efficiency": "high",
        "spec_source": "AMD product brief"
      },
      {
        "id": "cpu_intel_xeon_w5_2455x",
        "brand": "Intel",
        "model": "Xeon W5-2455X",
        "socket": "LGA4677",
        "cores": 12,
        "threads": 24,
        "base_clock_ghz": 3.1,
        "boost_ghz": 4.6,
        "tdp_w": 120,
        "msrp_rub": 175000,
        "use_cases": ["workstation", "3d_rendering", "professional_work"],
        "performance_score": 92,
        "power_efficiency": "medium",
        "spec_source": "Intel ARK / product pages"
      },
      {
        "id": "cpu_amd_threadripper_pro_7955wx",
        "brand": "AMD",
        "model": "Ryzen Threadripper PRO 7955WX",
        "socket": "sWRX8",
        "cores": 16,
        "threads": 32,
        "base_clock_ghz": 4.0,
        "boost_ghz": 5.1,
        "tdp_w": 350,
        "msrp_rub": 450000,
        "use_cases": ["professional_workstations", "3d_rendering", "ai_development"],
        "performance_score": 96,
        "power_efficiency": "low",
        "spec_source": "AMD product brief"
      },
      {
        "id": "cpu_intel_core_i3_15100",
        "brand": "Intel",
        "model": "Core i3-15100",
        "socket": "LGA1851",
        "cores": 4,
        "threads": 8,
        "base_clock_ghz": 3.6,
        "boost_ghz": 4.8,
        "tdp_w": 60,
        "msrp_rub": 15200,
        "use_cases": ["office_work", "student", "light_tasks"],
        "performance_score": 68,
        "power_efficiency": "very_high",
        "spec_source": "Intel ARK / product pages"
      },
      {
        "id": "cpu_amd_ryzen_7_8700g",
        "brand": "AMD",
        "model": "Ryzen 7 8700G",
        "socket": "AM5",
        "cores": 8,
        "threads": 16,
        "base_clock_ghz": 4.2,
        "boost_ghz": 5.1,
        "tdp_w": 65,
        "msrp_rub": 46000,
        "use_cases": ["gaming", "content_creation", "igpu"],
        "performance_score": 91,
        "power_efficiency": "high",
        "spec_source": "AMD product brief"
      },
      {
        "id": "cpu_intel_core_ultra_5_135h",
        "brand": "Intel",
        "model": "Core Ultra 5 135H",
        "socket": "BGA",
        "cores": 14,
        "threads": 18,
        "base_clock_ghz": 3.0,
        "boost_ghz": 4.6,
        "tdp_w": 45,
        "msrp_rub": 28000,
        "use_cases": ["mobile_workstations", "content_creation", "ai"],
        "performance_score": 83,
        "power_efficiency": "very_high",
        "spec_source": "Intel ARK / product pages"
      },
      {
        "id": "cpu_amd_ryzen_9_8945hs",
        "brand": "AMD",
        "model": "Ryzen 9 8945HS",
        "socket": "FP8",
        "cores": 8,
        "threads": 16,
        "base_clock_ghz": 4.0,
        "boost_ghz": 5.2,
        "tdp_w": 35,
        "msrp_rub": 38000,
        "use_cases": ["premium_laptops", "content_creation", "gaming"],
        "performance_score": 89,
        "power_efficiency": "very_high",
        "spec_source": "AMD product brief"
      },
      {
        "id": "cpu_intel_pentium_gold_g7400",
        "brand": "Intel",
        "model": "Pentium Gold G7400",
        "socket": "LGA1700",
        "cores": 2,
        "threads": 4,
        "base_clock_ghz": 3.7,
        "boost_ghz": 4.2,
        "tdp_w": 46,
        "msrp_rub": 5800,
        "use_cases": ["home_office", "basic_computing", "student"],
        "performance_score": 45,
        "power_efficiency": "high",
        "spec_source": "Intel ARK / product pages"
      },
      {
        "id": "cpu_amd_athlon_gold_7220u",
        "brand": "AMD",
        "model": "Athlon Gold 7220U",
        "socket": "FP7",
        "cores": 2,
        "threads": 4,
        "base_clock_ghz": 2.4,
        "boost_ghz": 3.7,
        "tdp_w": 15,
        "msrp_rub": 4200,
        "use_cases": ["budget_laptops", "student", "basic_tasks"],
        "performance_score": 38,
        "power_efficiency": "very_high",
        "spec_source": "AMD product brief"
      },
      {
        "id": "cpu_intel_celeron_g6900",
        "brand": "Intel",
        "model": "Celeron G6900",
        "socket": "LGA1700",
        "cores": 2,
        "threads": 2,
        "base_clock_ghz": 3.4,
        "boost_ghz": 3.4,
        "tdp_w": 46,
        "msrp_rub": 3500,
        "use_cases": ["basic_office", "home_computing", "low_budget"],
        "performance_score": 35,
        "power_efficiency": "medium",
        "spec_source": "Intel ARK / product pages"
      },
      {
        "id": "cpu_intel_core_i9_15900ks",
        "brand": "Intel",
        "model": "Core i9-15900KS",
        "socket": "LGA1851",
        "cores": 24,
        "threads": 32,
        "base_clock_ghz": 3.5,
        "boost_ghz": 6.2,
        "tdp_w": 150,
        "msrp_rub": 89000,
        "use_cases": ["enthusiast_gaming", "content_creation", "extreme_performance"],
        "performance_score": 99,
        "power_efficiency": "low",
        "spec_source": "Intel ARK / product pages"
      },
      {
        "id": "cpu_amd_ryzen_threadripper_7980x",
        "brand": "AMD",
        "model": "Ryzen Threadripper 7980X",
        "socket": "sTR5",
        "cores": 64,
        "threads": 128,
        "base_clock_ghz": 3.2,
        "boost_ghz": 5.1,
        "tdp_w": 350,
        "msrp_rub": 1250000,
        "use_cases": ["professional_workstations", "scientific_computing", "simulation"],
        "performance_score": 100,
        "power_efficiency": "low",
        "spec_source": "AMD product brief"
      },
      {
        "id": "cpu_intel_xeon_w9_3495x",
        "brand": "Intel",
        "model": "Xeon W9-3495X",
        "socket": "LGA4677",
        "cores": 56,
        "threads": 112,
        "base_clock_ghz": 2.3,
        "boost_ghz": 4.8,
        "tdp_w": 350,
        "msrp_rub": 1750000,
        "use_cases": ["high_end_workstations", "simulation", "ai_research"],
        "performance_score": 100,
        "power_efficiency": "low",
        "spec_source": "Intel ARK / product pages"
      },
      {
        "id": "cpu_amd_epyc_9754",
        "brand": "AMD",
        "model": "EPYC 9754",
        "socket": "SP5",
        "cores": 128,
        "threads": 256,
        "base_clock_ghz": 2.2,
        "boost_ghz": 3.8,
        "tdp_w": 360,
        "msrp_rub": 3500000,
        "use_cases": ["datacenters", "cloud_computing", "enterprise_servers"],
        "performance_score": 100,
        "power_efficiency": "medium",
        "spec_source": "AMD product brief"
      },
      {
        "id": "cpu_intel_core_i5_15600kf",
        "brand": "Intel",
        "model": "Core i5-15600KF",
        "socket": "LGA1851",
        "cores": 14,
        "threads": 20,
        "base_clock_ghz": 3.5,
        "boost_ghz": 5.3,
        "tdp_w": 125,
        "msrp_rub": 36500,
        "use_cases": ["gaming", "streaming", "content_creation"],
        "performance_score": 89,
        "power_efficiency": "medium",
        "spec_source": "Intel ARK / product pages"
      },
      {
        "id": "cpu_amd_ryzen_5_9500",
        "brand": "AMD",
        "model": "Ryzen 5 9500",
        "socket": "AM5",
        "cores": 6,
        "threads": 12,
        "base_clock_ghz": 4.4,
        "boost_ghz": 5.3,
        "tdp_w": 65,
        "msrp_rub": 24500,
        "use_cases": ["gaming", "office_work", "budget_builds"],
        "performance_score": 85,
        "power_efficiency": "high",
        "spec_source": "AMD product brief"
      },
      {
        "id": "cpu_intel_core_ultra_7_255h",
        "brand": "Intel",
        "model": "Core Ultra 7 255H",
        "socket": "BGA",
        "cores": 16,
        "threads": 22,
        "base_clock_ghz": 3.2,
        "boost_ghz": 4.8,
        "tdp_w": 45,
        "msrp_rub": 42000,
        "use_cases": ["premium_laptops", "content_creation", "ai_acceleration"],
        "performance_score": 87,
        "power_efficiency": "very_high",
        "spec_source": "Intel ARK / product pages"
      },
      {
        "id": "cpu_amd_ryzen_7_9700g",
        "brand": "AMD",
        "model": "Ryzen 7 9700G",
        "socket": "AM5",
        "cores": 8,
        "threads": 16,
        "base_clock_ghz": 4.5,
        "boost_ghz": 5.4,
        "tdp_w": 65,
        "msrp_rub": 44500,
        "use_cases": ["gaming", "content_creation", "igpu"],
        "performance_score": 92,
        "power_efficiency": "high",
        "spec_source": "AMD product brief"
      },
      {
        "id": "cpu_intel_core_i7_15700kf",
        "brand": "Intel",
        "model": "Core i7-15700KF",
        "socket": "LGA1851",
        "cores": 16,
        "threads": 24,
        "base_clock_ghz": 3.5,
        "boost_ghz": 5.5,
        "tdp_w": 125,
        "msrp_rub": 54000,
        "use_cases": ["gaming", "content_creation", "streaming"],
        "performance_score": 94,
        "power_efficiency": "medium",
        "spec_source": "Intel ARK / product pages"
      },
      {
        "id": "cpu_amd_ryzen_9_9900",
        "brand": "AMD",
        "model": "Ryzen 9 9900",
        "socket": "AM5",
        "cores": 12,
        "threads": 24,
        "base_clock_ghz": 4.7,
        "boost_ghz": 5.6,
        "tdp_w": 65,
        "msrp_rub": 57500,
        "use_cases": ["content_creation", "gaming", "professional_work"],
        "performance_score": 95,
        "power_efficiency": "high",
        "spec_source": "AMD product brief"
      },
      {
        "id": "cpu_intel_xeon_w7_2475x",
        "brand": "Intel",
        "model": "Xeon W7-2475X",
        "socket": "LGA4677",
        "cores": 20,
        "threads": 40,
        "base_clock_ghz": 3.3,
        "boost_ghz": 4.8,
        "tdp_w": 165,
        "msrp_rub": 320000,
        "use_cases": ["professional_workstations", "cad", "engineering"],
        "performance_score": 94,
        "power_efficiency": "medium",
        "spec_source": "Intel ARK / product pages"
      },
      {
        "id": "cpu_amd_ryzen_threadripper_pro_7995wx",
        "brand": "AMD",
        "model": "Ryzen Threadripper PRO 7995WX",
        "socket": "sWRX8",
        "cores": 96,
        "threads": 192,
        "base_clock_ghz": 3.0,
        "boost_ghz": 5.1,
        "tdp_w": 350,
        "msrp_rub": 1900000,
        "use_cases": ["high_end_workstations", "simulation", "rendering_farms"],
        "performance_score": 100,
        "power_efficiency": "low",
        "spec_source": "AMD product brief"
      },
      {
        "id": "cpu_intel_core_i3_15100f",
        "brand": "Intel",
        "model": "Core i3-15100F",
        "socket": "LGA1851",
        "cores": 4,
        "threads": 8,
        "base_clock_ghz": 3.6,
        "boost_ghz": 4.8,
        "tdp_w": 58,
        "msrp_rub": 11500,
        "use_cases": ["budget_gaming", "office_work", "student"],
        "performance_score": 67,
        "power_efficiency": "very_high",
        "spec_source": "Intel ARK / product pages"
      },
      {
        "id": "cpu_amd_ryzen_5_8500g",
        "brand": "AMD",
        "model": "Ryzen 5 8500G",
        "socket": "AM5",
        "cores": 6,
        "threads": 12,
        "base_clock_ghz": 4.1,
        "boost_ghz": 5.0,
        "tdp_w": 65,
        "msrp_rub": 27500,
        "use_cases": ["gaming", "office_work", "igpu"],
        "performance_score": 82,
        "power_efficiency": "high",
        "spec_source": "AMD product brief"
      },
      {
        "id": "cpu_intel_core_i5_14500t",
        "brand": "Intel",
        "model": "Core i5-14500T",
        "socket": "LGA1700",
        "cores": 14,
        "threads": 20,
        "base_clock_ghz": 2.1,
        "boost_ghz": 4.8,
        "tdp_w": 35,
        "msrp_rub": 22000,
        "use_cases": ["office_work", "silent_systems", "home_theaters"],
        "performance_score": 78,
        "power_efficiency": "very_high",
        "spec_source": "Intel ARK / product pages"
      },
      {
        "id": "cpu_amd_a10_9700",
        "brand": "AMD",
        "model": "A10-9700",
        "socket": "AM4",
        "cores": 4,
        "threads": 4,
        "base_clock_ghz": 3.5,
        "boost_ghz": 3.8,
        "tdp_w": 65,
        "msrp_rub": 3200,
        "use_cases": ["legacy_systems", "office_work", "budget_builds"],
        "performance_score": 42,
        "power_efficiency": "low",
        "spec_source": "AMD product brief"
      },
      {
        "id": "cpu_intel_pentium_g6405",
        "brand": "Intel",
        "model": "Pentium G6405",
        "socket": "LGA1200",
        "cores": 2,
        "threads": 4,
        "base_clock_ghz": 4.1,
        "boost_ghz": 4.1,
        "tdp_w": 58,
        "msrp_rub": 2800,
        "use_cases": ["office_work", "home_use", "retro_gaming"],
        "performance_score": 36,
        "power_efficiency": "medium",
        "spec_source": "Intel ARK / product pages"
      },
      {
        "id": "cpu_amd_athlon_3000g",
        "brand": "AMD",
        "model": "Athlon 3000G",
        "socket": "AM4",
        "cores": 2,
        "threads": 4,
        "base_clock_ghz": 3.5,
        "boost_ghz": 3.5,
        "tdp_w": 35,
        "msrp_rub": 2500,
        "use_cases": ["budget_office", "retro_gaming", "light_tasks"],
        "performance_score": 32,
        "power_efficiency": "high",
        "spec_source": "AMD product brief"
      },
      {
        "id": "cpu_intel_core_i7_10700k",
        "brand": "Intel",
        "model": "Core i7-10700K",
        "socket": "LGA1200",
        "cores": 8,
        "threads": 16,
        "base_clock_ghz": 3.8,
        "boost_ghz": 5.1,
        "tdp_w": 125,
        "msrp_rub": 18500,
        "use_cases": ["gaming", "content_creation", "legacy_systems"],
        "performance_score": 80,
        "power_efficiency": "low",
        "spec_source": "Intel ARK / product pages"
      },
      {
        "id": "cpu_amd_ryzen_7_3700x",
        "brand": "AMD",
        "model": "Ryzen 7 3700X",
        "socket": "AM4",
        "cores": 8,
        "threads": 16,
        "base_clock_ghz": 3.6,
        "boost_ghz": 4.4,
        "tdp_w": 65,
        "msrp_rub": 15500,
        "use_cases": ["gaming", "content_creation", "budget_high_performance"],
        "performance_score": 82,
        "power_efficiency": "high",
        "spec_source": "AMD product brief"
      },
      {
        "id": "cpu_intel_core_i5_10400f",
        "brand": "Intel",
        "model": "Core i5-10400F",
        "socket": "LGA1200",
        "cores": 6,
        "threads": 12,
        "base_clock_ghz": 2.9,
        "boost_ghz": 4.3,
        "tdp_w": 65,
        "msrp_rub": 9500,
        "use_cases": ["gaming", "office_work", "budget_systems"],
        "performance_score": 72,
        "power_efficiency": "high",
        "spec_source": "Intel ARK / product pages"
      },
      {
        "id": "cpu_amd_ryzen_5_3600xt",
        "brand": "AMD",
        "model": "Ryzen 5 3600XT",
        "socket": "AM4",
        "cores": 6,
        "threads": 12,
        "base_clock_ghz": 3.8,
        "boost_ghz": 4.5,
        "tdp_w": 95,
        "msrp_rub": 13800,
        "use_cases": ["gaming", "content_creation", "budget_high_performance"],
        "performance_score": 78,
        "power_efficiency": "medium",
        "spec_source": "AMD product brief"
      },
      {
        "id": "cpu_intel_core_i9_11900k",
        "brand": "Intel",
        "model": "Core i9-11900K",
        "socket": "LGA1200",
        "cores": 8,
        "threads": 16,
        "base_clock_ghz": 3.5,
        "boost_ghz": 5.3,
        "tdp_w": 125,
        "msrp_rub": 32000,
        "use_cases": ["gaming", "content_creation", "high_performance"],
        "performance_score": 86,
        "power_efficiency": "low",
        "spec_source": "Intel ARK / product pages"
      },
      {
        "id": "cpu_amd_ryzen_9_3900x",
        "brand": "AMD",
        "model": "Ryzen 9 3900X",
        "socket": "AM4",
        "cores": 12,
        "threads": 24,
        "base_clock_ghz": 3.8,
        "boost_ghz": 4.6,
        "tdp_w": 105,
        "msrp_rub": 34500,
        "use_cases": ["content_creation", "gaming", "professional_work"],
        "performance_score": 88,
        "power_efficiency": "medium",
        "spec_source": "AMD product brief"
      },
      {
        "id": "cpu_intel_xeon_e5_2689",
        "brand": "Intel",
        "model": "Xeon E5-2689",
        "socket": "LGA2011",
        "cores": 8,
        "threads": 16,
        "base_clock_ghz": 2.6,
        "boost_ghz": 3.6,
        "tdp_w": 115,
        "msrp_rub": 8500,
        "use_cases": ["server_upgrades", "budget_workstations", "virtualization"],
        "performance_score": 65,
        "power_efficiency": "low",
        "spec_source": "Intel ARK / specialized sellers"
      },
      {
        "id": "cpu_amd_opteron_6386_se",
        "brand": "AMD",
        "model": "Opteron 6386 SE",
        "socket": "G34",
        "cores": 16,
        "threads": 16,
        "base_clock_ghz": 2.8,
        "boost_ghz": 3.5,
        "tdp_w": 140,
        "msrp_rub": 12000,
        "use_cases": ["server_systems", "budget_hpc", "legacy_infrastructure"],
        "performance_score": 60,
        "power_efficiency": "low",
        "spec_source": "AMD product brief / specialized sellers"
      },
      {
        "id": "cpu_intel_core_i7_9700k",
        "brand": "Intel",
        "model": "Core i7-9700K",
        "socket": "LGA1151",
        "cores": 8,
        "threads": 8,
        "base_clock_ghz": 3.6,
        "boost_ghz": 4.9,
        "tdp_w": 90,
        "msrp_rub": 16500,
        "use_cases": ["gaming", "content_creation", "legacy_systems"],
        "performance_score": 78,
        "power_efficiency": "medium",
        "spec_source": "Intel ARK / product pages"
      },
      {
        "id": "cpu_amd_ryzen_7_2700x",
        "brand": "AMD",
        "model": "Ryzen 7 2700X",
        "socket": "AM4",
        "cores": 8,
        "threads": 16,
        "base_clock_ghz": 3.7,
        "boost_ghz": 4.3,
        "tdp_w": 105,
        "msrp_rub": 14000,
        "use_cases": ["gaming", "content_creation", "budget_high_performance"],
        "performance_score": 77,
        "power_efficiency": "medium",
        "spec_source": "AMD product brief"
      },
      {
        "id": "cpu_intel_core_i5_9600k",
        "brand": "Intel",
        "model": "Core i5-9600K",
        "socket": "LGA1151",
        "cores": 6,
        "threads": 6,
        "base_clock_ghz": 3.7,
        "boost_ghz": 4.6,
        "tdp_w": 95,
        "msrp_rub": 12500,
        "use_cases": ["gaming", "office_work", "legacy_builds"],
        "performance_score": 73,
        "power_efficiency": "medium",
        "spec_source": "Intel ARK / product pages"
      },
      {
        "id": "cpu_amd_ryzen_5_2600x",
        "brand": "AMD",
        "model": "Ryzen 5 2600X",
        "socket": "AM4",
        "cores": 6,
        "threads": 12,
        "base_clock_ghz": 3.6,
        "boost_ghz": 4.2,
        "tdp_w": 95,
        "msrp_rub": 11000,
        "use_cases": ["gaming", "content_creation", "budget_builds"],
        "performance_score": 74,
        "power_efficiency": "medium",
        "spec_source": "AMD product brief"
      },
      {
        "id": "cpu_intel_core_i3_10100",
        "brand": "Intel",
        "model": "Core i3-10100",
        "socket": "LGA1200",
        "cores": 4,
        "threads": 8,
        "base_clock_ghz": 3.6,
        "boost_ghz": 4.3,
        "tdp_w": 65,
        "msrp_rub": 8500,
        "use_cases": ["office_work", "student", "budget_gaming"],
        "performance_score": 62,
        "power_efficiency": "high",
        "spec_source": "Intel ARK / product pages"
      },
      {
        "id": "cpu_amd_ryzen_3_3100",
        "brand": "AMD",
        "model": "Ryzen 3 3100",
        "socket": "AM4",
        "cores": 4,
        "threads": 8,
        "base_clock_ghz": 3.6,
        "boost_ghz": 3.9,
        "tdp_w": 65,
        "msrp_rub": 7800,
        "use_cases": ["budget_gaming", "office_work", "student"],
        "performance_score": 60,
        "power_efficiency": "high",
        "spec_source": "AMD product brief"
      },
      {
        "id": "cpu_intel_core_i7_12700kf",
        "brand": "Intel",
        "model": "Core i7-12700KF",
        "socket": "LGA1700",
        "cores": 12,
        "threads": 20,
        "base_clock_ghz": 3.6,
        "boost_ghz": 5.0,
        "tdp_w": 125,
        "msrp_rub": 29500,
        "use_cases": ["gaming", "content_creation", "streaming"],
        "performance_score": 89,
        "power_efficiency": "medium",
        "spec_source": "Intel ARK / product pages"
      },
      {
        "id": "cpu_amd_ryzen_5_7500f",
        "brand": "AMD",
        "model": "Ryzen 5 7500F",
        "socket": "AM5",
        "cores": 6,
        "threads": 12,
        "base_clock_ghz": 4.2,
        "boost_ghz": 5.0,
        "tdp_w": 65,
        "msrp_rub": 16500,
        "use_cases": ["gaming", "office_work", "budget"],
        "performance_score": 81,
        "power_efficiency": "high",
        "spec_source": "AMD product brief"
      },
      {
        "id": "cpu_intel_core_i9_14900kf",
        "brand": "Intel",
        "model": "Core i9-14900KF",
        "socket": "LGA1700",
        "cores": 24,
        "threads": 32,
        "base_clock_ghz": 3.2,
        "boost_ghz": 6.0,
        "tdp_w": 125,
        "msrp_rub": 65000,
        "use_cases": ["gaming", "content_creation", "high_performance"],
        "performance_score": 98,
        "power_efficiency": "low",
        "spec_source": "Intel ARK / product pages"
      },
      {
        "id": "cpu_amd_ryzen_7_7700x",
        "brand": "AMD",
        "model": "Ryzen 7 7700X",
        "socket": "AM5",
        "cores": 8,
        "threads": 16,
        "base_clock_ghz": 4.5,
        "boost_ghz": 5.4,
        "tdp_w": 105,
        "msrp_rub": 35500,
        "use_cases": ["gaming", "content_creation", "professional_work"],
        "performance_score": 90,
        "power_efficiency": "medium",
        "spec_source": "AMD product brief"
      },
      {
        "id": "cpu_intel_core_i5_13500h",
        "brand": "Intel",
        "model": "Core i5-13500H",
        "socket": "BGA",
        "cores": 12,
        "threads": 16,
        "base_clock_ghz": 2.6,
        "boost_ghz": 4.7,
        "tdp_w": 45,
        "msrp_rub": 18500,
        "use_cases": ["mobile_workstations", "gaming_laptops", "content_creation"],
        "performance_score": 81,
        "power_efficiency": "high",
        "spec_source": "Intel ARK / product pages"
      },
      {
        "id": "cpu_amd_ryzen_9_7940hs",
        "brand": "AMD",
        "model": "Ryzen 9 7940HS",
        "socket": "FP8",
        "cores": 8,
        "threads": 16,
        "base_clock_ghz": 4.0,
        "boost_ghz": 5.2,
        "tdp_w": 35,
        "msrp_rub": 45000,
        "use_cases": ["premium_laptops", "content_creation", "gaming"],
        "performance_score": 88,
        "power_efficiency": "very_high",
        "spec_source": "AMD product brief"
      },
      {
        "id": "cpu_intel_xeon_e3_1270_v5",
        "brand": "Intel",
        "model": "Xeon E3-1270 v5",
        "socket": "LGA1151",
        "cores": 4,
        "threads": 8,
        "base_clock_ghz": 3.6,
        "boost_ghz": 4.0,
        "tdp_w": 80,
        "msrp_rub": 9500,
        "use_cases": ["workstation", "server_entry_level", "budget_professional"],
        "performance_score": 68,
        "power_efficiency": "medium",
        "spec_source": "Intel ARK / specialized sellers"
      },
      {
        "id": "cpu_amd_epyc_7302p",
        "brand": "AMD",
        "model": "EPYC 7302P",
        "socket": "SP3",
        "cores": 16,
        "threads": 32,
        "base_clock_ghz": 3.0,
        "boost_ghz": 3.3,
        "tdp_w": 155,
        "msrp_rub": 98000,
        "use_cases": ["server_systems", "virtualization", "data_processing"],
        "performance_score": 82,
        "power_efficiency": "medium",
        "spec_source": "AMD product brief / specialized sellers"
      },
      {
        "id": "cpu_intel_core_i5_11600kf",
        "brand": "Intel",
        "model": "Core i5-11600KF",
        "socket": "LGA1200",
        "cores": 6,
        "threads": 12,
        "base_clock_ghz": 3.9,
        "boost_ghz": 4.9,
        "tdp_w": 125,
        "msrp_rub": 15500,
        "use_cases": ["gaming", "content_creation", "budget_high_performance"],
        "performance_score": 79,
        "power_efficiency": "medium",
        "spec_source": "Intel ARK / product pages"
      },
      {
        "id": "cpu_amd_ryzen_7_5800x",
        "brand": "AMD",
        "model": "Ryzen 7 5800X",
        "socket": "AM4",
        "cores": 8,
        "threads": 16,
        "base_clock_ghz": 3.8,
        "boost_ghz": 4.7,
        "tdp_w": 105,
        "msrp_rub": 22500,
        "use_cases": ["gaming", "content_creation", "professional_work"],
        "performance_score": 85,
        "power_efficiency": "medium",
        "spec_source": "AMD product brief"
      },
      {
        "id": "cpu_intel_core_i3_12300",
        "brand": "Intel",
        "model": "Core i3-12300",
        "socket": "LGA1700",
        "cores": 4,
        "threads": 8,
        "base_clock_ghz": 3.3,
        "boost_ghz": 4.4,
        "tdp_w": 60,
        "msrp_rub": 11500,
        "use_cases": ["office_work", "student", "light_gaming"],
        "performance_score": 63,
        "power_efficiency": "high",
        "spec_source": "Intel ARK / product pages"
      },
      {
        "id": "cpu_amd_ryzen_5_5600g",
        "brand": "AMD",
        "model": "Ryzen 5 5600G",
        "socket": "AM4",
        "cores": 6,
        "threads": 12,
        "base_clock_ghz": 3.9,
        "boost_ghz": 4.4,
        "tdp_w": 65,
        "msrp_rub": 12500,
        "use_cases": ["office_work", "light_gaming", "igpu"],
        "performance_score": 75,
        "power_efficiency": "high",
        "spec_source": "AMD product brief"
      },
      {
        "id": "cpu_intel_core_i9_14900hx",
        "brand": "Intel",
        "model": "Core i9-14900HX",
        "socket": "BGA",
        "cores": 24,
        "threads": 32,
        "base_clock_ghz": 2.2,
        "boost_ghz": 5.8,
        "tdp_w": 55,
        "msrp_rub": 72000,
        "use_cases": ["premium_laptops", "mobile_gaming", "content_creation"],
        "performance_score": 96,
        "power_efficiency": "medium",
        "spec_source": "Intel ARK / product pages"
      },
      {
        "id": "cpu_amd_ryzen_9_7945hx",
        "brand": "AMD",
        "model": "Ryzen 9 7945HX",
        "socket": "FL1",
        "cores": 16,
        "threads": 32,
        "base_clock_ghz": 2.5,
        "boost_ghz": 5.4,
        "tdp_w": 55,
        "msrp_rub": 85000,
        "use_cases": ["premium_laptops", "mobile_workstations", "content_creation"],
        "performance_score": 97,
        "power_efficiency": "medium",
        "spec_source": "AMD product brief"
      },
      {
        "id": "cpu_intel_core_ultra_9_275k",
        "brand": "Intel",
        "model": "Core Ultra 9 275K",
        "socket": "LGA1851",
        "cores": 24,
        "threads": 28,
        "base_clock_ghz": 3.8,
        "boost_ghz": 5.6,
        "tdp_w": 125,
        "msrp_rub": 58000,
        "use_cases": ["gaming", "content_creation", "ai_acceleration"],
        "performance_score": 94,
        "power_efficiency": "high",
        "spec_source": "Intel ARK / product pages"
      },
      {
        "id": "cpu_amd_ryzen_threadripper_7970x",
        "brand": "AMD",
        "model": "Ryzen Threadripper 7970X",
        "socket": "sTR5",
        "cores": 32,
        "threads": 64,
        "base_clock_ghz": 4.0,
        "boost_ghz": 5.3,
        "tdp_w": 350,
        "msrp_rub": 750000,
        "use_cases": ["professional_workstations", "3d_rendering", "simulation"],
        "performance_score": 98,
        "power_efficiency": "low",
        "spec_source": "AMD product brief"
      },
      {
        "id": "cpu_intel_xeon_gold_6430",
        "brand": "Intel",
        "model": "Xeon Gold 6430",
        "socket": "LGA4677",
        "cores": 32,
        "threads": 64,
        "base_clock_ghz": 2.1,
        "boost_ghz": 3.4,
        "tdp_w": 320,
        "msrp_rub": 550000,
        "use_cases": ["datacenters", "high_performance_computing", "enterprise"],
        "performance_score": 91,
        "power_efficiency": "medium",
        "spec_source": "Intel ARK / specialized sellers"
      },
      {
        "id": "cpu_amd_epyc_9654",
        "brand": "AMD",
        "model": "EPYC 9654",
        "socket": "SP5",
        "cores": 96,
        "threads": 192,
        "base_clock_ghz": 2.4,
        "boost_ghz": 3.7,
        "tdp_w": 360,
        "msrp_rub": 2800000,
        "use_cases": ["datacenters", "cloud_computing", "enterprise_servers"],
        "performance_score": 100,
        "power_efficiency": "medium",
        "spec_source": "AMD product brief"
      },
      {
        "id": "cpu_intel_core_i5_14400t",
        "brand": "Intel",
        "model": "Core i5-14400T",
        "socket": "LGA1700",
        "cores": 10,
        "threads": 16,
        "base_clock_ghz": 1.9,
        "boost_ghz": 4.6,
        "tdp_w": 35,
        "msrp_rub": 19000,
        "use_cases": ["office_work", "silent_systems", "home_theaters"],
        "performance_score": 76,
        "power_efficiency": "very_high",
        "spec_source": "Intel ARK / product pages"
      },
      {
        "id": "cpu_amd_ryzen_5_8600",
        "brand": "AMD",
        "model": "Ryzen 5 8600",
        "socket": "AM5",
        "cores": 6,
        "threads": 12,
        "base_clock_ghz": 4.3,
        "boost_ghz": 5.2,
        "tdp_w": 65,
        "msrp_rub": 29000,
        "use_cases": ["gaming", "office_work", "content_creation"],
        "performance_score": 86,
        "power_efficiency": "high",
        "spec_source": "AMD product brief"
      },
      {
        "id": "cpu_intel_core_i7_15700",
        "brand": "Intel",
        "model": "Core i7-15700",
        "socket": "LGA1851",
        "cores": 16,
        "threads": 24,
        "base_clock_ghz": 3.0,
        "boost_ghz": 5.2,
        "tdp_w": 65,
        "msrp_rub": 42000,
        "use_cases": ["content_creation", "gaming", "professional_work"],
        "performance_score": 92,
        "power_efficiency": "high",
        "spec_source": "Intel ARK / product pages"
      },
      {
        "id": "cpu_amd_ryzen_9_8900",
        "brand": "AMD",
        "model": "Ryzen 9 8900",
        "socket": "AM5",
        "cores": 12,
        "threads": 24,
        "base_clock_ghz": 4.1,
        "boost_ghz": 5.4,
        "tdp_w": 65,
        "msrp_rub": 51000,
        "use_cases": ["content_creation", "professional_work", "gaming"],
        "performance_score": 94,
        "power_efficiency": "high",
        "spec_source": "AMD product brief"
      },
      {
        "id": "cpu_intel_core_i3_14100t",
        "brand": "Intel",
        "model": "Core i3-14100T",
        "socket": "LGA1700",
        "cores": 4,
        "threads": 8,
        "base_clock_ghz": 2.5,
        "boost_ghz": 4.4,
        "tdp_w": 35,
        "msrp_rub": 12500,
        "use_cases": ["office_work", "budget_systems", "silent_computing"],
        "performance_score": 62,
        "power_efficiency": "very_high",
        "spec_source": "Intel ARK / product pages"
      },
      {
        "id": "cpu_amd_ryzen_7_8700",
        "brand": "AMD",
        "model": "Ryzen 7 8700",
        "socket": "AM5",
        "cores": 8,
        "threads": 16,
        "base_clock_ghz": 4.1,
        "boost_ghz": 5.1,
        "tdp_w": 65,
        "msrp_rub": 38500,
        "use_cases": ["gaming", "content_creation", "professional_work"],
        "performance_score": 90,
        "power_efficiency": "high",
        "spec_source": "AMD product brief"
      },
      {
        "id": "cpu_intel_core_ultra_3_125h",
        "brand": "Intel",
        "model": "Core Ultra 3 125H",
        "socket": "BGA",
        "cores": 10,
        "threads": 12,
        "base_clock_ghz": 3.0,
        "boost_ghz": 4.5,
        "tdp_w": 15,
        "msrp_rub": 16500,
        "use_cases": ["ultrabooks", "office_work", "student_laptops"],
        "performance_score": 72,
        "power_efficiency": "very_high",
        "spec_source": "Intel ARK / product pages"
      },
      {
        "id": "cpu_amd_ryzen_5_8500",
        "brand": "AMD",
        "model": "Ryzen 5 8500",
        "socket": "AM5",
        "cores": 6,
        "threads": 12,
        "base_clock_ghz": 4.0,
        "boost_ghz": 5.0,
        "tdp_w": 65,
        "msrp_rub": 23500,
        "use_cases": ["gaming", "office_work", "budget_builds"],
        "performance_score": 83,
        "power_efficiency": "high",
        "spec_source": "AMD product brief"
      },
      {
        "id": "cpu_intel_xeon_w5_3423",
        "brand": "Intel",
        "model": "Xeon W5-3423",
        "socket": "LGA4677",
        "cores": 12,
        "threads": 24,
        "base_clock_ghz": 2.8,
        "boost_ghz": 4.3,
        "tdp_w": 120,
        "msrp_rub": 145000,
        "use_cases": ["professional_workstations", "cad", "content_creation"],
        "performance_score": 88,
        "power_efficiency": "medium",
        "spec_source": "Intel ARK / specialized sellers"
      },
      {
        "id": "cpu_amd_ryzen_threadripper_pro_7965wx",
        "brand": "AMD",
        "model": "Ryzen Threadripper PRO 7965WX",
        "socket": "sWRX8",
        "cores": 24,
        "threads": 48,
        "base_clock_ghz": 4.0,
        "boost_ghz": 5.1,
        "tdp_w": 350,
        "msrp_rub": 620000,
        "use_cases": ["professional_workstations", "3d_rendering", "simulation"],
        "performance_score": 95,
        "power_efficiency": "low",
        "spec_source": "AMD product brief"
      },
      {
        "id": "cpu_intel_core_i5_14500",
        "brand": "Intel",
        "model": "Core i5-14500",
        "socket": "LGA1700",
        "cores": 14,
        "threads": 20,
        "base_clock_ghz": 2.5,
        "boost_ghz": 5.0,
        "tdp_w": 65,
        "msrp_rub": 24500,
        "use_cases": ["gaming", "office_work", "content_creation"],
        "performance_score": 85,
        "power_efficiency": "high",
        "spec_source": "Intel ARK / product pages"
      },
      {
        "id": "cpu_amd_ryzen_5_9500f",
        "brand": "AMD",
        "model": "Ryzen 5 9500F",
        "socket": "AM5",
        "cores": 6,
        "threads": 12,
        "base_clock_ghz": 4.3,
        "boost_ghz": 5.2,
        "tdp_w": 65,
        "msrp_rub": 23000,
        "use_cases": ["gaming", "content_creation", "budget_builds"],
        "performance_score": 84,
        "power_efficiency": "high",
        "spec_source": "AMD product brief"
      },
      {
        "id": "cpu_intel_core_i7_15700t",
        "brand": "Intel",
        "model": "Core i7-15700T",
        "socket": "LGA1851",
        "cores": 16,
        "threads": 24,
        "base_clock_ghz": 2.1,
        "boost_ghz": 4.9,
        "tdp_w": 35,
        "msrp_rub": 38000,
        "use_cases": ["office_work", "content_creation", "silent_systems"],
        "performance_score": 86,
        "power_efficiency": "very_high",
        "spec_source": "Intel ARK / product pages"
      },
      {
        "id": "cpu_amd_ryzen_9_9900x3d",
        "brand": "AMD",
        "model": "Ryzen 9 9900X3D",
        "socket": "AM5",
        "cores": 12,
        "threads": 24,
        "base_clock_ghz": 4.4,
        "boost_ghz": 5.5,
        "tdp_w": 120,
        "msrp_rub": 72000,
        "use_cases": ["gaming", "content_creation", "high_performance"],
        "performance_score": 97,
        "power_efficiency": "high",
        "spec_source": "AMD product brief"
      },
      {
        "id": "cpu_intel_core_i3_15300",
        "brand": "Intel",
        "model": "Core i3-15300",
        "socket": "LGA1851",
        "cores": 4,
        "threads": 8,
        "base_clock_ghz": 3.8,
        "boost_ghz": 5.0,
        "tdp_w": 60,
        "msrp_rub": 17500,
        "use_cases": ["office_work", "student", "light_gaming"],
        "performance_score": 70,
        "power_efficiency": "high",
        "spec_source": "Intel ARK / product pages"
      },
      {
        "id": "cpu_amd_ryzen_7_9700xf",
        "brand": "AMD",
        "model": "Ryzen 7 9700XF",
        "socket": "AM5",
        "cores": 8,
        "threads": 16,
        "base_clock_ghz": 4.8,
        "boost_ghz": 5.6,
        "tdp_w": 105,
        "msrp_rub": 41000,
        "use_cases": ["gaming", "content_creation", "professional_work"],
        "performance_score": 93,
        "power_efficiency": "medium",
        "spec_source": "AMD product brief"
      },
      {
        "id": "cpu_intel_celeron_g7400t",
        "brand": "Intel",
        "model": "Celeron G7400T",
        "socket": "LGA1700",
        "cores": 2,
        "threads": 2,
        "base_clock_ghz": 3.0,
        "boost_ghz": 3.0,
        "tdp_w": 35,
        "msrp_rub": 2800,
        "use_cases": ["basic_office", "home_computing", "low_power_systems"],
        "performance_score": 32,
        "power_efficiency": "high",
        "spec_source": "Intel ARK / product pages"
      },
      {
        "id": "cpu_amd_athlon_gold_g34",
        "brand": "AMD",
        "model": "Athlon Gold 3150U",
        "socket": "FP6",
        "cores": 2,
        "threads": 4,
        "base_clock_ghz": 2.3,
        "boost_ghz": 3.3,
        "tdp_w": 15,
        "msrp_rub": 3500,
        "use_cases": ["budget_laptops", "student", "basic_tasks"],
        "performance_score": 35,
        "power_efficiency": "very_high",
        "spec_source": "AMD product brief"
      },
      {
        "id": "cpu_intel_pentium_gold_g8400",
        "brand": "Intel",
        "model": "Pentium Gold G8400",
        "socket": "LGA1700",
        "cores": 2,
        "threads": 4,
        "base_clock_ghz": 3.9,
        "boost_ghz": 4.3,
        "tdp_w": 46,
        "msrp_rub": 6200,
        "use_cases": ["office_work", "basic_computing", "student"],
        "performance_score": 48,
        "power_efficiency": "high",
        "spec_source": "Intel ARK / product pages"
      },
      {
        "id": "cpu_amd_a4_9120",
        "brand": "AMD",
        "model": "A4-9120",
        "socket": "FP5",
        "cores": 2,
        "threads": 2,
        "base_clock_ghz": 2.2,
        "boost_ghz": 2.5,
        "tdp_w": 15,
        "msrp_rub": 2200,
        "use_cases": ["ultra_budget", "basic_tasks", "older_systems"],
        "performance_score": 22,
        "power_efficiency": "very_high",
        "spec_source": "AMD product brief"
      },
      {
        "id": "cpu_intel_core_i7_12800hx",
        "brand": "Intel",
        "model": "Core i7-12800HX",
        "socket": "BGA",
        "cores": 16,
        "threads": 24,
        "base_clock_ghz": 2.0,
        "boost_ghz": 4.8,
        "tdp_w": 55,
        "msrp_rub": 38000,
        "use_cases": ["gaming_laptops", "mobile_workstations", "content_creation"],
        "performance_score": 87,
        "power_efficiency": "medium",
        "spec_source": "Intel ARK / product pages"
      },
      {
        "id": "cpu_amd_ryzen_7_7840hs",
        "brand": "AMD",
        "model": "Ryzen 7 7840HS",
        "socket": "FP8",
        "cores": 8,
        "threads": 16,
        "base_clock_ghz": 3.8,
        "boost_ghz": 5.1,
        "tdp_w": 35,
        "msrp_rub": 42000,
        "use_cases": ["premium_laptops", "gaming", "content_creation"],
        "performance_score": 88,
        "power_efficiency": "very_high",
        "spec_source": "AMD product brief"
      },
      {
        "id": "cpu_intel_xeon_e5_2696_v4",
        "brand": "Intel",
        "model": "Xeon E5-2696 v4",
        "socket": "LGA2011-3",
        "cores": 22,
        "threads": 44,
        "base_clock_ghz": 2.2,
        "boost_ghz": 3.6,
        "tdp_w": 145,
        "msrp_rub": 35000,
        "use_cases": ["server_systems", "virtualization", "legacy_infrastructure"],
        "performance_score": 75,
        "power_efficiency": "low",
        "spec_source": "Intel ARK / specialized sellers"
      },
      {
        "id": "cpu_amd_ryzen_threadripper_3970x",
        "brand": "AMD",
        "model": "Ryzen Threadripper 3970X",
        "socket": "sTRX4",
        "cores": 32,
        "threads": 64,
        "base_clock_ghz": 3.7,
        "boost_ghz": 4.5,
        "tdp_w": 280,
        "msrp_rub": 251000,
        "use_cases": ["professional_workstations", "3d_rendering", "simulation"],
        "performance_score": 96,
        "power_efficiency": "low",
        "spec_source": "AMD product brief"
      },
      {
        "id": "cpu_intel_core_i7_13700e",
        "brand": "Intel",
        "model": "Core i7-13700E",
        "socket": "LGA1700",
        "cores": 16,
        "threads": 24,
        "base_clock_ghz": 2.1,
        "boost_ghz": 5.1,
        "tdp_w": 65,
        "msrp_rub": 45000,
        "use_cases": ["embedded_systems", "industrial_computing", "specialized_systems"],
        "performance_score": 89,
        "power_efficiency": "high",
        "spec_source": "Intel ARK / product pages"
      },
      {
        "id": "cpu_amd_epyc_7742",
        "brand": "AMD",
        "model": "EPYC 7742",
        "socket": "SP3",
        "cores": 64,
        "threads": 128,
        "base_clock_ghz": 2.2,
        "boost_ghz": 3.4,
        "tdp_w": 225,
        "msrp_rub": 1200000,
        "use_cases": ["datacenters", "high_performance_computing", "enterprise"],
        "performance_score": 96,
        "power_efficiency": "medium",
        "spec_source": "AMD product brief"
      },
      {
        "id": "cpu_intel_core_i5_12600t",
        "brand": "Intel",
        "model": "Core i5-12600T",
        "socket": "LGA1700",
        "cores": 10,
        "threads": 16,
        "base_clock_ghz": 2.1,
        "boost_ghz": 4.7,
        "tdp_w": 35,
        "msrp_rub": 18500,
        "use_cases": ["office_work", "content_creation", "silent_systems"],
        "performance_score": 78,
        "power_efficiency": "very_high",
        "spec_source": "Intel ARK / product pages"
      },
      {
        "id": "cpu_amd_ryzen_5_5600xt",
        "brand": "AMD",
        "model": "Ryzen 5 5600XT",
        "socket": "AM4",
        "cores": 6,
        "threads": 12,
        "base_clock_ghz": 3.8,
        "boost_ghz": 4.5,
        "tdp_w": 95,
        "msrp_rub": 13500,
        "use_cases": ["gaming", "content_creation", "budget_builds"],
        "performance_score": 77,
        "power_efficiency": "medium",
        "spec_source": "AMD product brief"
      },
      {
        "id": "cpu_intel_core_i9_14900xe",
        "brand": "Intel",
        "model": "Core i9-14900XE",
        "socket": "LGA2066",
        "cores": 18,
        "threads": 36,
        "base_clock_ghz": 3.0,
        "boost_ghz": 4.8,
        "tdp_w": 165,
        "msrp_rub": 95000,
        "use_cases": ["high_end_workstations", "professional_content_creation", "simulation"],
        "performance_score": 94,
        "power_efficiency": "low",
        "spec_source": "Intel ARK / product pages"
      },
      {
        "id": "cpu_amd_ryzen_9_7900",
        "brand": "AMD",
        "model": "Ryzen 9 7900",
        "socket": "AM5",
        "cores": 12,
        "threads": 24,
        "base_clock_ghz": 3.8,
        "boost_ghz": 5.4,
        "tdp_w": 65,
        "msrp_rub": 56000,
        "use_cases": ["content_creation", "gaming", "professional_work"],
        "performance_score": 94,
        "power_efficiency": "high",
        "spec_source": "AMD product brief"
      },
      {
        "id": "cpu_intel_core_i3_1705",
        "brand": "Intel",
        "model": "Core i3-1705",
        "socket": "LGA1700",
        "cores": 4,
        "threads": 4,
        "base_clock_ghz": 3.5,
        "boost_ghz": 4.3,
        "tdp_w": 60,
        "msrp_rub": 11000,
        "use_cases": ["office_work", "light_computing", "budget_builds"],
        "performance_score": 58,
        "power_efficiency": "high",
        "spec_source": "Intel ARK / product pages"
      },
      {
        "id": "cpu_amd_ryzen_threadripper_pro_5995wx",
        "brand": "AMD",
        "model": "Ryzen Threadripper PRO 5995WX",
        "socket": "sWRX8",
        "cores": 64,
        "threads": 128,
        "base_clock_ghz": 2.7,
        "boost_ghz": 4.5,
        "tdp_w": 280,
        "msrp_rub": 850000,
        "use_cases": ["professional_workstations", "3d_rendering", "simulation"],
        "performance_score": 98,
        "power_efficiency": "low",
        "spec_source": "AMD product brief"
      },
      {
        "id": "cpu_intel_xeon_w7_3465x",
        "brand": "Intel",
        "model": "Xeon W7-3465X",
        "socket": "LGA4677",
        "cores": 28,
        "threads": 56,
        "base_clock_ghz": 2.9,
        "boost_ghz": 4.7,
        "tdp_w": 220,
        "msrp_rub": 280000,
        "use_cases": ["professional_workstations", "simulation", "rendering"],
        "performance_score": 95,
        "power_efficiency": "low",
        "spec_source": "Intel ARK / specialized sellers"
      },
      {
        "id": "cpu_amd_ryzen_5_9500x",
        "brand": "AMD",
        "model": "Ryzen 5 9500X",
        "socket": "AM5",
        "cores": 6,
        "threads": 12,
        "base_clock_ghz": 4.5,
        "boost_ghz": 5.5,
        "tdp_w": 105,
        "msrp_rub": 28500,
        "use_cases": ["gaming", "content_creation", "office_work"],
        "performance_score": 87,
        "power_efficiency": "medium",
        "spec_source": "AMD product brief"
      },
      {
        "id": "cpu_intel_core_i7_15700kf",
        "brand": "Intel",
        "model": "Core i7-15700KF",
        "socket": "LGA1851",
        "cores": 16,
        "threads": 24,
        "base_clock_ghz": 3.5,
        "boost_ghz": 5.5,
        "tdp_w": 125,
        "msrp_rub": 54000,
        "use_cases": ["gaming", "content_creation", "streaming"],
        "performance_score": 94,
        "power_efficiency": "medium",
        "spec_source": "Intel ARK / product pages"
      },
      {
        "id": "cpu_amd_ryzen_7_8700f",
        "brand": "AMD",
        "model": "Ryzen 7 8700F",
        "socket": "AM5",
        "cores": 8,
        "threads": 16,
        "base_clock_ghz": 4.1,
        "boost_ghz": 5.0,
        "tdp_w": 65,
        "msrp_rub": 36000,
        "use_cases": ["gaming", "content_creation", "budget_high_performance"],
        "performance_score": 89,
        "power_efficiency": "high",
        "spec_source": "AMD product brief"
      },
      {
        "id": "cpu_intel_core_i9_13900xe",
        "brand": "Intel",
        "model": "Core i9-13900XE",
        "socket": "LGA2066",
        "cores": 18,
        "threads": 36,
        "base_clock_ghz": 2.9,
        "boost_ghz": 4.8,
        "tdp_w": 165,
        "msrp_rub": 92000,
        "use_cases": ["high_end_workstations", "professional_content_creation", "simulation"],
        "performance_score": 93,
        "power_efficiency": "low",
        "spec_source": "Intel ARK / product pages"
      },
      {
        "id": "cpu_amd_ryzen_9_7950x3d",
        "brand": "AMD",
        "model": "Ryzen 9 7950X3D",
        "socket": "AM5",
        "cores": 16,
        "threads": 32,
        "base_clock_ghz": 4.2,
        "boost_ghz": 5.7,
        "tdp_w": 120,
        "msrp_rub": 68000,
        "use_cases": ["gaming", "content_creation", "high_performance"],
        "performance_score": 97,
        "power_efficiency": "high",
        "spec_source": "AMD product brief"
      },
      {
        "id": "cpu_intel_core_i5_14600kf",
        "brand": "Intel",
        "model": "Core i5-14600KF",
        "socket": "LGA1700",
        "cores": 14,
        "threads": 20,
        "base_clock_ghz": 3.5,
        "boost_ghz": 5.3,
        "tdp_w": 125,
        "msrp_rub": 32000,
        "use_cases": ["gaming", "streaming", "content_creation"],
        "performance_score": 90,
        "power_efficiency": "medium",
        "spec_source": "Intel ARK / product pages"
      },
      {
        "id": "cpu_amd_ryzen_7_7800xt",
        "brand": "AMD",
        "model": "Ryzen 7 7800XT",
        "socket": "AM5",
        "cores": 8,
        "threads": 16,
        "base_clock_ghz": 4.6,
        "boost_ghz": 5.3,
        "tdp_w": 128,
        "msrp_rub": 42500,
        "use_cases": ["gaming", "content_creation", "professional_work"],
        "performance_score": 94,
        "power_efficiency": "medium",
        "spec_source": "AMD product brief"
      }
    ]
  }